taiga_contrib_fas_openid_auth
