Metadata-Version: 1.1
Name: taiga-contrib-fas-openid-auth
Version: 0.3
Summary: The Taiga plugin for FAS authentication
Home-page: https://github.com/fedora-infra/taiga-contrib-fas-openid-auth
Author: Ralph Bean
Author-email: rbean@redhat.com
License: AGPL
Keywords: taiga,fas,openid,fedora,auth,plugin
Platform: UNKNOWN
Classifier: Programming Language :: Python
Classifier: Development Status :: 4 - Beta
Classifier: Framework :: Django
Classifier: Intended Audience :: Developers
Classifier: License :: OSI Approved :: GNU Affero General Public License v3
Classifier: Operating System :: OS Independent
Classifier: Programming Language :: Python
Classifier: Topic :: Internet :: WWW/HTTP
